{
  "Q01": {
    "S": 1,
    "M": 2,
    "SD": 2,
    "V": -2,
    "C": 1,
    "KD": 2,
    "L": 1,
    "MP": -1
  },
  "Q02": {
    "S": 2,
    "M": 1,
    "SD": 2,
    "V": -2,
    "C": -1,
    "KD": 2,
    "L": 1,
    "MP": -2
  },
  "Q03": {
    "S": 2,
    "M": 2,
    "SD": 2,
    "V": -2,
    "C": 1,
    "KD": 2,
    "L": 2,
    "MP": -1
  },
  "Q04": {
    "S": 2,
    "M": 1,
    "SD": 2,
    "V": -2,
    "C": 1,
    "KD": 2,
    "L": 2,
    "MP": -1
  },
  "Q05": {
    "S": 1,
    "M": 2,
    "SD": 2,
    "V": -2,
    "C": 0,
    "KD": 2,
    "L": 1,
    "MP": -1
  },
  "Q06": {
    "S": 2,
    "M": 2,
    "SD": 2,
    "V": -2,
    "C": 1,
    "KD": 2,
    "L": 2,
    "MP": -1
  },
  "Q07": {
    "S": 0,
    "M": 2,
    "SD": 2,
    "V": -2,
    "C": 0,
    "KD": 2,
    "L": 1,
    "MP": -2
  },
  "Q08": {
    "S": 1,
    "M": 2,
    "SD": 2,
    "V": -2,
    "C": 0,
    "KD": 2,
    "L": 2,
    "MP": -2
  },
  "Q09": {
    "S": 2,
    "M": 0,
    "SD": 1,
    "V": 2,
    "C": -1,
    "KD": 0,
    "L": 1,
    "MP": 1
  },
  "Q10": {
    "S": 1,
    "M": -2,
    "SD": -1,
    "V": 2,
    "C": -2,
    "KD": -2,
    "L": -2,
    "MP": 1
  },
  "Q11": {
    "S": -1,
    "M": 1,
    "SD": 1,
    "V": -2,
    "C": 2,
    "KD": 1,
    "L": 2,
    "MP": -1
  },
  "Q12": {
    "S": 0,
    "M": 1,
    "SD": 1,
    "V": -2,
    "C": 1,
    "KD": 1,
    "L": 2,
    "MP": -1
  },
  "Q13": {
    "S": 0,
    "M": 2,
    "SD": 2,
    "V": -2,
    "C": 1,
    "KD": 1,
    "L": 1,
    "MP": -1
  },
  "Q14": {
    "S": 2,
    "M": -2,
    "SD": -1,
    "V": 2,
    "C": -1,
    "KD": -1,
    "L": -2,
    "MP": 2
  },
  "Q15": {
    "S": 0,
    "M": 2,
    "SD": 1,
    "V": -2,
    "C": 2,
    "KD": 1,
    "L": 2,
    "MP": -1
  },
  "Q16": {
    "S": 1,
    "M": -1,
    "SD": 0,
    "V": 2,
    "C": 0,
    "KD": 0,
    "L": 0,
    "MP": 1
  },
  "Q17": {
    "S": 1,
    "M": 2,
    "SD": 2,
    "V": -2,
    "C": 0,
    "KD": 1,
    "L": 2,
    "MP": -2
  },
  "Q18": {
    "S": -1,
    "M": 2,
    "SD": 2,
    "V": -2,
    "C": 1,
    "KD": 2,
    "L": 1,
    "MP": -2
  },
  "Q19": {
    "S": 1,
    "M": -1,
    "SD": -2,
    "V": 2,
    "C": 1,
    "KD": -1,
    "L": 0,
    "MP": 2
  },
  "Q20": {
    "S": 1,
    "M": 1,
    "SD": -2,
    "V": -1,
    "C": 2,
    "KD": 0,
    "L": 2,
    "MP": 1
  }
}
